paulis/__init__.py
paulis/py.typed
paulis-0.0.post1.dist-info/LICENSE
paulis-0.0.post1.dist-info/METADATA
paulis-0.0.post1.dist-info/WHEEL
paulis-0.0.post1.dist-info/top_level.txt
paulis-0.0.post1.dist-info/RECORD
